{
  "filename": "container_wordbank",
  "title": "Container Wordbank 2017",
  "documentId": "container_wordbank",
  "phrases": [
    {
      "phrase": "",
      "phraseToParse": "amphora",
      "imgData": {
        "url": ""
      },
      "metaData": {}
    },
    {
      "phrase": "",
      "phraseToParse": "attache case",
      "imgData": {
        "url": ""
      },
      "metaData": {}
    },
    {
      "phrase": "",
      "phraseToParse": "backpack",
      "imgData": {
        "url": ""
      },
      "metaData": {}
    },
    {
      "phrase": "",
      "phraseToParse": "bag",
      "imgData": {
        "url": ""
      },
      "metaData": {}
    },
    {
      "phrase": "",
      "phraseToParse": "baggage",
      "imgData": {
        "url": ""
      },
      "metaData": {}
    },
    {
      "phrase": "",
      "phraseToParse": "barrel",
      "imgData": {
        "url": ""
      },
      "metaData": {}
    },
    {
      "phrase": "",
      "phraseToParse": "basin",
      "imgData": {
        "url": ""
      },
      "metaData": {}
    },
    {
      "phrase": "",
      "phraseToParse": "basket",
      "imgData": {
        "url": ""
      },
      "metaData": {}
    },
    {
      "phrase": "",
      "phraseToParse": "beaker",
      "imgData": {
        "url": ""
      },
      "metaData": {}
    },
    {
      "phrase": "",
      "phraseToParse": "bin",
      "imgData": {
        "url": ""
      },
      "metaData": {}
    },
    {
      "phrase": "",
      "phraseToParse": "bottle",
      "imgData": {
        "url": ""
      },
      "metaData": {}
    },
    {
      "phrase": "",
      "phraseToParse": "bowl",
      "imgData": {
        "url": ""
      },
      "metaData": {}
    },
    {
      "phrase": "",
      "phraseToParse": "box",
      "imgData": {
        "url": ""
      },
      "metaData": {}
    },
    {
      "phrase": "",
      "phraseToParse": "briefcase",
      "imgData": {
        "url": ""
      },
      "metaData": {}
    },
    {
      "phrase": "",
      "phraseToParse": "bucket",
      "imgData": {
        "url": ""
      },
      "metaData": {}
    },
    {
      "phrase": "",
      "phraseToParse": "cabinet",
      "imgData": {
        "url": ""
      },
      "metaData": {}
    },
    {
      "phrase": "",
      "phraseToParse": "can",
      "imgData": {
        "url": ""
      },
      "metaData": {}
    },
    {
      "phrase": "",
      "phraseToParse": "canister",
      "imgData": {
        "url": ""
      },
      "metaData": {}
    },
    {
      "phrase": "",
      "phraseToParse": "canteen",
      "imgData": {
        "url": ""
      },
      "metaData": {}
    },
    {
      "phrase": "",
      "phraseToParse": "carafe",
      "imgData": {
        "url": ""
      },
      "metaData": {}
    },
    {
      "phrase": "",
      "phraseToParse": "carrier",
      "imgData": {
        "url": ""
      },
      "metaData": {}
    },
    {
      "phrase": "",
      "phraseToParse": "carryall",
      "imgData": {
        "url": ""
      },
      "metaData": {}
    },
    {
      "phrase": "",
      "phraseToParse": "carton",
      "imgData": {
        "url": ""
      },
      "metaData": {}
    },
    {
      "phrase": "",
      "phraseToParse": "case",
      "imgData": {
        "url": ""
      },
      "metaData": {}
    },
    {
      "phrase": "",
      "phraseToParse": "cask",
      "imgData": {
        "url": ""
      },
      "metaData": {}
    },
    {
      "phrase": "",
      "phraseToParse": "casket",
      "imgData": {
        "url": ""
      },
      "metaData": {}
    },
    {
      "phrase": "",
      "phraseToParse": "chest",
      "imgData": {
        "url": ""
      },
      "metaData": {}
    },
    {
      "phrase": "",
      "phraseToParse": "coffer",
      "imgData": {
        "url": ""
      },
      "metaData": {}
    },
    {
      "phrase": "",
      "phraseToParse": "cone",
      "imgData": {
        "url": ""
      },
      "metaData": {}
    },
    {
      "phrase": "",
      "phraseToParse": "container",
      "imgData": {
        "url": ""
      },
      "metaData": {}
    },
    {
      "phrase": "",
      "phraseToParse": "compote",
      "imgData": {
        "url": ""
      },
      "metaData": {}
    },
    {
      "phrase": "",
      "phraseToParse": "cooler",
      "imgData": {
        "url": ""
      },
      "metaData": {}
    },
    {
      "phrase": "",
      "phraseToParse": "crate",
      "imgData": {
        "url": ""
      },
      "metaData": {}
    },
    {
      "phrase": "",
      "phraseToParse": "crock",
      "imgData": {
        "url": ""
      },
      "metaData": {}
    },
    {
      "phrase": "",
      "phraseToParse": "cruet",
      "imgData": {
        "url": ""
      },
      "metaData": {}
    },
    {
      "phrase": "",
      "phraseToParse": "cube",
      "imgData": {
        "url": ""
      },
      "metaData": {}
    },
    {
      "phrase": "",
      "phraseToParse": "depository",
      "imgData": {
        "url": ""
      },
      "metaData": {}
    },
    {
      "phrase": "",
      "phraseToParse": "dish",
      "imgData": {
        "url": ""
      },
      "metaData": {}
    },
    {
      "phrase": "",
      "phraseToParse": "drawer",
      "imgData": {
        "url": ""
      },
      "metaData": {}
    },
    {
      "phrase": "",
      "phraseToParse": "drum",
      "imgData": {
        "url": ""
      },
      "metaData": {}
    },
    {
      "phrase": "",
      "phraseToParse": "enclosure",
      "imgData": {
        "url": ""
      },
      "metaData": {}
    },
    {
      "phrase": "",
      "phraseToParse": "envelope",
      "imgData": {
        "url": ""
      },
      "metaData": {}
    },
    {
      "phrase": "",
      "phraseToParse": "ewer",
      "imgData": {
        "url": ""
      },
      "metaData": {}
    },
    {
      "phrase": "",
      "phraseToParse": "file folder",
      "imgData": {
        "url": ""
      },
      "metaData": {}
    },
    {
      "phrase": "",
      "phraseToParse": "flask",
      "imgData": {
        "url": ""
      },
      "metaData": {}
    },
    {
      "phrase": "",
      "phraseToParse": "folder",
      "imgData": {
        "url": ""
      },
      "metaData": {}
    },
    {
      "phrase": "",
      "phraseToParse": "garbage can",
      "imgData": {
        "url": ""
      },
      "metaData": {}
    },
    {
      "phrase": "",
      "phraseToParse": "glass",
      "imgData": {
        "url": ""
      },
      "metaData": {}
    },
    {
      "phrase": "",
      "phraseToParse": "goblet",
      "imgData": {
        "url": ""
      },
      "metaData": {}
    },
    {
      "phrase": "",
      "phraseToParse": "grocery bag",
      "imgData": {
        "url": ""
      },
      "metaData": {}
    },
    {
      "phrase": "",
      "phraseToParse": "hamper",
      "imgData": {
        "url": ""
      },
      "metaData": {}
    },
    {
      "phrase": "",
      "phraseToParse": "handbag",
      "imgData": {
        "url": ""
      },
      "metaData": {}
    },
    {
      "phrase": "",
      "phraseToParse": "holder",
      "imgData": {
        "url": ""
      },
      "metaData": {}
    },
    {
      "phrase": "",
      "phraseToParse": "hopper",
      "imgData": {
        "url": ""
      },
      "metaData": {}
    },
    {
      "phrase": "",
      "phraseToParse": "hutch",
      "imgData": {
        "url": ""
      },
      "metaData": {}
    },
    {
      "phrase": "",
      "phraseToParse": "ice bucket",
      "imgData": {
        "url": ""
      },
      "metaData": {}
    },
    {
      "phrase": "",
      "phraseToParse": "jar",
      "imgData": {
        "url": ""
      },
      "metaData": {}
    },
    {
      "phrase": "",
      "phraseToParse": "jug",
      "imgData": {
        "url": ""
      },
      "metaData": {}
    },
    {
      "phrase": "",
      "phraseToParse": "knapsack",
      "imgData": {
        "url": ""
      },
      "metaData": {}
    },
    {
      "phrase": "",
      "phraseToParse": "locker",
      "imgData": {
        "url": ""
      },
      "metaData": {}
    },
    {
      "phrase": "",
      "phraseToParse": "luggage",
      "imgData": {
        "url": ""
      },
      "metaData": {}
    },
    {
      "phrase": "",
      "phraseToParse": "lunchbox",
      "imgData": {
        "url": ""
      },
      "metaData": {}
    },
    {
      "phrase": "",
      "phraseToParse": "milk crate",
      "imgData": {
        "url": ""
      },
      "metaData": {}
    },
    {
      "phrase": "",
      "phraseToParse": "packet",
      "imgData": {
        "url": ""
      },
      "metaData": {}
    },
    {
      "phrase": "",
      "phraseToParse": "pail",
      "imgData": {
        "url": ""
      },
      "metaData": {}
    },
    {
      "phrase": "",
      "phraseToParse": "pan",
      "imgData": {
        "url": ""
      },
      "metaData": {}
    },
    {
      "phrase": "",
      "phraseToParse": "paper bag",
      "imgData": {
        "url": ""
      },
      "metaData": {}
    },
    {
      "phrase": "",
      "phraseToParse": "plastic bag",
      "imgData": {
        "url": ""
      },
      "metaData": {}
    },
    {
      "phrase": "",
      "phraseToParse": "plate",
      "imgData": {
        "url": ""
      },
      "metaData": {}
    },
    {
      "phrase": "",
      "phraseToParse": "pocket",
      "imgData": {
        "url": ""
      },
      "metaData": {}
    },
    {
      "phrase": "",
      "phraseToParse": "pod",
      "imgData": {
        "url": ""
      },
      "metaData": {}
    },
    {
      "phrase": "",
      "phraseToParse": "pot",
      "imgData": {
        "url": ""
      },
      "metaData": {}
    },
    {
      "phrase": "",
      "phraseToParse": "pouch",
      "imgData": {
        "url": ""
      },
      "metaData": {}
    },
    {
      "phrase": "",
      "phraseToParse": "purse",
      "imgData": {
        "url": ""
      },
      "metaData": {}
    },
    {
      "phrase": "",
      "phraseToParse": "rack",
      "imgData": {
        "url": ""
      },
      "metaData": {}
    },
    {
      "phrase": "",
      "phraseToParse": "receptacle",
      "imgData": {
        "url": ""
      },
      "metaData": {}
    },
    {
      "phrase": "",
      "phraseToParse": "sack",
      "imgData": {
        "url": ""
      },
      "metaData": {}
    },
    {
      "phrase": "",
      "phraseToParse": "saddlebag",
      "imgData": {
        "url": ""
      },
      "metaData": {}
    },
    {
      "phrase": "",
      "phraseToParse": "satchel",
      "imgData": {
        "url": ""
      },
      "metaData": {}
    },
    {
      "phrase": "",
      "phraseToParse": "saucer",
      "imgData": {
        "url": ""
      },
      "metaData": {}
    },
    {
      "phrase": "",
      "phraseToParse": "stein",
      "imgData": {
        "url": ""
      },
      "metaData": {}
    },
    {
      "phrase": "",
      "phraseToParse": "suitcase",
      "imgData": {
        "url": ""
      },
      "metaData": {}
    },
    {
      "phrase": "",
      "phraseToParse": "tin",
      "imgData": {
        "url": ""
      },
      "metaData": {}
    },
    {
      "phrase": "",
      "phraseToParse": "tote",
      "imgData": {
        "url": ""
      },
      "metaData": {}
    },
    {
      "phrase": "",
      "phraseToParse": "trash bin",
      "imgData": {
        "url": ""
      },
      "metaData": {}
    },
    {
      "phrase": "",
      "phraseToParse": "trunk",
      "imgData": {
        "url": ""
      },
      "metaData": {}
    },
    {
      "phrase": "",
      "phraseToParse": "tray",
      "imgData": {
        "url": ""
      },
      "metaData": {}
    },
    {
      "phrase": "",
      "phraseToParse": "tub",
      "imgData": {
        "url": ""
      },
      "metaData": {}
    },
    {
      "phrase": "",
      "phraseToParse": "tube",
      "imgData": {
        "url": ""
      },
      "metaData": {}
    },
    {
      "phrase": "",
      "phraseToParse": "tun",
      "imgData": {
        "url": ""
      },
      "metaData": {}
    },
    {
      "phrase": "",
      "phraseToParse": "tureen",
      "imgData": {
        "url": ""
      },
      "metaData": {}
    },
    {
      "phrase": "",
      "phraseToParse": "test tube",
      "imgData": {
        "url": ""
      },
      "metaData": {}
    },
    {
      "phrase": "",
      "phraseToParse": "urn",
      "imgData": {
        "url": ""
      },
      "metaData": {}
    },
    {
      "phrase": "",
      "phraseToParse": "vase",
      "imgData": {
        "url": ""
      },
      "metaData": {}
    },
    {
      "phrase": "",
      "phraseToParse": "vat",
      "imgData": {
        "url": ""
      },
      "metaData": {}
    },
    {
      "phrase": "",
      "phraseToParse": "vault",
      "imgData": {
        "url": ""
      },
      "metaData": {}
    },
    {
      "phrase": "",
      "phraseToParse": "vesicle",
      "imgData": {
        "url": ""
      },
      "metaData": {}
    },
    {
      "phrase": "",
      "phraseToParse": "vessel",
      "imgData": {
        "url": ""
      },
      "metaData": {}
    },
    {
      "phrase": "",
      "phraseToParse": "vial",
      "imgData": {
        "url": ""
      },
      "metaData": {}
    },
    {
      "phrase": "",
      "phraseToParse": "wastebasket",
      "imgData": {
        "url": ""
      },
      "metaData": {}
    },
    {
      "phrase": "",
      "phraseToParse": "water bottle",
      "imgData": {
        "url": ""
      },
      "metaData": {}
    }
  ]
}
